wemeet_openapi/__init__.py
wemeet_openapi/client.py
wemeet_openapi/core/__init__.py
wemeet_openapi/core/authenticator.py
wemeet_openapi/core/config.py
wemeet_openapi/core/constants.py
wemeet_openapi/core/exception.py
wemeet_openapi/core/serializer.py
wemeet_openapi/core/utils.py
wemeet_openapi/core/version.py
wemeet_openapi/core/xhttp/__init__.py
wemeet_openapi/core/xhttp/authenticator.py
wemeet_openapi/core/xhttp/client.py
wemeet_openapi/core/xhttp/client_test.py
wemeet_openapi/core/xhttp/request.py
wemeet_openapi/core/xhttp/response.py
wemeet_openapi/core/xhttp/serializer.py
wemeet_openapi/service/__init__.py
wemeet_openapi/service/application_group/__init__.py
wemeet_openapi/service/application_group/api.py
wemeet_openapi/service/application_group/model.py
wemeet_openapi/service/layout/__init__.py
wemeet_openapi/service/layout/api.py
wemeet_openapi/service/layout/model.py
wemeet_openapi/service/meeting_control/__init__.py
wemeet_openapi/service/meeting_control/api.py
wemeet_openapi/service/meeting_control/model.py
wemeet_openapi/service/meeting_guest/__init__.py
wemeet_openapi/service/meeting_guest/api.py
wemeet_openapi/service/meeting_guest/model.py
wemeet_openapi/service/meeting_room/__init__.py
wemeet_openapi/service/meeting_room/api.py
wemeet_openapi/service/meeting_room/model.py
wemeet_openapi/service/meetings/__init__.py
wemeet_openapi/service/meetings/api.py
wemeet_openapi/service/meetings/model.py
wemeet_openapi/service/pstn/__init__.py
wemeet_openapi/service/pstn/api.py
wemeet_openapi/service/pstn/model.py
wemeet_openapi/service/record_intelligence/__init__.py
wemeet_openapi/service/record_intelligence/api.py
wemeet_openapi/service/record_intelligence/model.py
wemeet_openapi/service/records/__init__.py
wemeet_openapi/service/records/api.py
wemeet_openapi/service/records/model.py
wemeet_openapi/service/user_manager/__init__.py
wemeet_openapi/service/user_manager/api.py
wemeet_openapi/service/user_manager/model.py
wemeet_openapi_sdk_python-1.0.10.dist-info/licenses/LICENSE
wemeet_openapi_sdk_python-1.0.10.dist-info/METADATA
wemeet_openapi_sdk_python-1.0.10.dist-info/WHEEL
wemeet_openapi_sdk_python-1.0.10.dist-info/top_level.txt
wemeet_openapi_sdk_python-1.0.10.dist-info/RECORD
