Metadata-Version: 2.4
Name: wemeet-openapi-sdk-python
Version: 1.0.10
Summary: OpenAPI SDK for Python
Home-page: https://github.com/TencentCloud/wemeet-openapi-sdk-python
Author: Wemeet
Author-email: wemeet@tencent.com
Project-URL: Source, https://github.com/TencentCloud/wemeet-openapi-sdk-python
Keywords: Wemeet,OpenAPI SDK
Requires-Python: >=3.7
License-File: LICENSE
Requires-Dist: requests
Dynamic: author
Dynamic: author-email
Dynamic: description
Dynamic: description-content-type
Dynamic: home-page
Dynamic: keywords
Dynamic: license-file
Dynamic: project-url
Dynamic: requires-dist
Dynamic: requires-python
Dynamic: summary
